src/forklift/__init__.py
src/forklift/forkliftlib/__init__.py
src/forklift/forkliftlib/confirm.py
src/forklift/forkliftlib/container.py
src/forklift/forkliftlib/inputBox.py
src/forklift/forkliftlib/menu.py
src/forklift/forkliftlib/messageBox.py
src/forklift/forkliftlib/screen.py
src/forklift/forkliftlib/textpad.py
forkliftcontainer-0.2.0.dist-info/METADATA
forkliftcontainer-0.2.0.dist-info/WHEEL
forkliftcontainer-0.2.0.dist-info/licenses/LICENSE
forkliftcontainer-0.2.0.dist-info/RECORD
