Metadata-Version: 2.1
Name: forkliftcontainer
Version: 0.2.0
Summary: Container friendly text-only curses utility (local and ssh usage)
Project-URL: Homepage, https://github.com/andreabenini/podmaster/tree/main/forklift
Project-URL: Bug Tracker, https://github.com/andreabenini/podmaster/issues
Author-email: Andrea Benini <andreabenini@gmail.com>
License-File: LICENSE
Classifier: License :: OSI Approved :: GNU Affero General Public License v3 or later (AGPLv3+)
Classifier: Operating System :: OS Independent
Classifier: Programming Language :: Python :: 3
Requires-Python: >=3.8
Requires-Dist: pyyaml
